.gitignore
LICENSE
readme.MD
setup.py
cpyder/__init__.py
cpyder/cpyder.py
cpyder/document_parser.py
cpyder/http_worker.py
cpyder/utils.py
cpyder.egg-info/PKG-INFO
cpyder.egg-info/SOURCES.txt
cpyder.egg-info/dependency_links.txt
cpyder.egg-info/requires.txt
cpyder.egg-info/top_level.txt
example/demo.py
example/data/mybb_cat.csv