Metadata-Version: 1.0
Name: cpyder
Version: 0.0.2
Summary: one simple but powerful crawler!
Home-page: https://github.com/spenly/cpyder
Author: spenly
Author-email: i@spenly.com
License: UNKNOWN
Platform: UNKNOWN
